LICENSE.txt
setup.py
spark_testing_base.egg-info/PKG-INFO
spark_testing_base.egg-info/SOURCES.txt
spark_testing_base.egg-info/dependency_links.txt
spark_testing_base.egg-info/requires.txt
spark_testing_base.egg-info/top_level.txt
sparktestingbase/__init__.py
sparktestingbase/pathmagic.py
sparktestingbase/sqltestcase.py
sparktestingbase/streamingtestcase.py
sparktestingbase/testcase.py
sparktestingbase/utils.py
sparktestingbase/test/__init__.py
sparktestingbase/test/helloworld_test.py
sparktestingbase/test/reuse_spark_context_test.py
sparktestingbase/test/simple_sql_test.py
sparktestingbase/test/simple_streaming_test.py
sparktestingbase/test/simple_test.py