Metadata-Version: 2.1
Name: spark-testing-base
Version: 0.11.0
Summary: Spark testing for python
Home-page: https://github.com/holdenk/spark-testing-base
Author: Holden Karau
Author-email: holden@pigscanfly.ca
License: LICENSE.txt
License-File: LICENSE.txt
Requires-Dist: findspark
Requires-Dist: pytest
